{
  "parent": "minecraft:recipes/root",
  "criteria": {
    "has_amethyst_shard": {
      "conditions": {
        "items": [
          {
            "items": [
              "minecraft:amethyst_shard"
            ]
          }
        ]
      },
      "trigger": "minecraft:inventory_changed"
    },
    "has_obsidian": {
      "conditions": {
        "items": [
          {
            "items": [
              "minecraft:obsidian"
            ]
          }
        ]
      },
      "trigger": "minecraft:inventory_changed"
    },
    "has_stone_brick_slab": {
      "conditions": {
        "items": [
          {
            "items": [
              "minecraft:stone_brick_slab"
            ]
          }
        ]
      },
      "trigger": "minecraft:inventory_changed"
    },
    "has_stone_bricks": {
      "conditions": {
        "items": [
          {
            "items": [
              "minecraft:stone_bricks"
            ]
          }
        ]
      },
      "trigger": "minecraft:inventory_changed"
    },
    "has_the_recipe": {
      "conditions": {
        "recipe": "myth_and_magic:rune_table"
      },
      "trigger": "minecraft:recipe_unlocked"
    }
  },
  "requirements": [
    [
      "has_obsidian",
      "has_amethyst_shard",
      "has_stone_bricks",
      "has_stone_brick_slab",
      "has_the_recipe"
    ]
  ],
  "rewards": {
    "recipes": [
      "myth_and_magic:rune_table"
    ]
  },
  "sends_telemetry_event": false
}